burdenoff_common/__init__.py
burdenoff_common/client.py
burdenoff_common/auth/__init__.py
burdenoff_common/auth/auth.py
burdenoff_common/billing/__init__.py
burdenoff_common/billing/addon.py
burdenoff_common/billing/billing.py
burdenoff_common/billing/payment.py
burdenoff_common/billing/plan.py
burdenoff_common/billing/quota.py
burdenoff_common/billing/usage.py
burdenoff_common/permissions/__init__.py
burdenoff_common/permissions/permissions.py
burdenoff_common/project/__init__.py
burdenoff_common/project/project.py
burdenoff_common/workspace/__init__.py
burdenoff_common/workspace/workspace.py
burdenoff_common-0.3.0.dist-info/METADATA
burdenoff_common-0.3.0.dist-info/WHEEL
burdenoff_common-0.3.0.dist-info/top_level.txt
burdenoff_common-0.3.0.dist-info/RECORD
