Metadata-Version: 2.4
Name: burdenoff-common
Version: 0.3.0
Summary: Python SDK for Burdenoff Workspace Server
Author-email: Burdenoff Team <info@burdenoff.com>
Project-URL: Homepage, https://github.com/burdenoff/burdenoff-common
Project-URL: Bug Tracker, https://github.com/burdenoff/burdenoff-common/issues
Classifier: Programming Language :: Python :: 3
Classifier: License :: OSI Approved :: MIT License
Classifier: Operating System :: OS Independent
Requires-Python: >=3.7
Requires-Dist: requests>=2.25.0
Requires-Dist: gql>=3.0.0
Requires-Dist: graphql-core>=3.1.0
Requires-Dist: pyjwt>=2.0.0
